r00buying_altcoins_monitoring/__init__.py
r00buying_altcoins_monitoring/main.py
r00buying_altcoins_monitoring/helpers/__init__.py
r00buying_altcoins_monitoring/helpers/constants.py
r00buying_altcoins_monitoring/helpers/data.json
r00buying_altcoins_monitoring-0.1.6.dist-info/METADATA
r00buying_altcoins_monitoring-0.1.6.dist-info/WHEEL
r00buying_altcoins_monitoring-0.1.6.dist-info/entry_points.txt
r00buying_altcoins_monitoring-0.1.6.dist-info/RECORD
