Metadata-Version: 2.4
Name: r00buying_altcoins_monitoring
Version: 0.1.6
Summary: Add your description here
Requires-Python: >=3.12
Requires-Dist: prettytable
Requires-Dist: python-coinmarketcap>=0.6
Requires-Dist: r00logger
Requires-Dist: r00notify
Requires-Dist: r00secret
